rs_template/__init__.py
rs_template/_command_line.py
rs_template/python_library.py
rs_template-0.2.0.dist-info/METADATA
rs_template-0.2.0.dist-info/WHEEL
rs_template-0.2.0.dist-info/entry_points.txt
rs_template-0.2.0.dist-info/licenses/LICENSE
rs_template-0.2.0.dist-info/RECORD
