Metadata-Version: 2.4
Name: rs-template
Version: 0.2.0
Summary: Template package for Reciprocal Space Station
Project-URL: homepage, https://rs-station.github.io/rs-template/
Project-URL: repository, https://github.com/rs-station/rs-template
Author-email: Dennis Brookner <debrookner@gmail.com>
License: BSD 3-Clause License
License-File: LICENSE
Classifier: Development Status :: 3 - Alpha
Classifier: License :: OSI Approved :: BSD License
Classifier: Natural Language :: English
Classifier: Programming Language :: Python :: 3
Classifier: Programming Language :: Python :: 3.9
Classifier: Programming Language :: Python :: 3.10
Classifier: Programming Language :: Python :: 3.11
Requires-Python: >=3.9
Requires-Dist: numpy
Requires-Dist: reciprocalspaceship>=1.0.1
Requires-Dist: tqdm
Provides-Extra: docs
Requires-Dist: myst-parser; extra == 'docs'
Requires-Dist: sphinx; extra == 'docs'
Requires-Dist: sphinx-rtd-theme; extra == 'docs'
Requires-Dist: sphinxcontrib-autoprogram; extra == 'docs'
Provides-Extra: test
Requires-Dist: pytest-cov; extra == 'test'
Requires-Dist: pytest>=6.0; extra == 'test'
